Workbook

Sheet Resumen
A1: Casa Yerko 250 m²
A2: Vivienda unifamiliar de dos niveles con local comercial — terreno de 300 m²
A4: CUADRO DE SUPERFICIES
A5: Concepto | B5: Unidad | C5: Cantidad
A6: Superficie del terreno | B6: m² | C6: 300
A7: Superficie cubierta planta baja | B7: m² | C7: 132
A8: Superficie cubierta planta alta | B8: m² | C8: 117.7
A9: Superficie cubierta total | B9: m² | C9: 249.7
A10: Balcón descubierto | B10: m² | C10: 14.56
A11: Superficie de ocupación en planta | B11: m² | C11: 132
A12: Porcentaje de ocupación | B12: % | C12: 44
A13: Área libre del terreno | B13: m² | C13: 168
A15: PROGRAMA ARQUITECTÓNICO
A16: Dormitorios | B16: 4 de 15,00 m² (uno en suite)
A17: Baños completos | B17: 4
A18: Sala – comedor | B18: 43,40 m²
A19: Cocina | B19: 17,28 m²
A20: Garaje | B20: 2 autos · 28,00 m²
A21: Tienda | B21: 14,00 m² con acceso desde la calle
A22: Lavandería | B22: 5,10 m²
A23: Churrasquera | B23: 3,50 × 3,00 m bajo pérgola
A24: Niveles | B24: 2 · altura libre 2,70 m y 2,60 m
A26: RESUMEN DE PRESUPUESTO (Bs)
A27: Capítulo | B27: Descripción | C27: Parcial Bs
A28: 1 | B28: TRABAJOS PRELIMINARES | C28: =Presupuesto!F5
A29: 2 | B29: MOVIMIENTO DE TIERRAS | C29: =Presupuesto!F8
A30: 3 | B30: OBRA GRUESA: HORMIGONES Y ESTRUCTURA | C30: =Presupuesto!F13
A31: 4 | B31: MAMPOSTERÍA Y CERRAMIENTOS | C31: =Presupuesto!F21
A32: 5 | B32: REVOQUES, CIELOS Y PINTURA | C32: =Presupuesto!F25
A33: 6 | B33: PISOS Y REVESTIMIENTOS | C33: =Presupuesto!F31
A34: 7 | B34: CUBIERTA | C34: =Presupuesto!F40
A35: 8 | B35: CARPINTERÍA | C35: =Presupuesto!F43
A36: 9 | B36: INSTALACIÓN SANITARIA Y AGUA | C36: =Presupuesto!F49
A37: 10 | B37: INSTALACIÓN ELÉCTRICA | C37: =Presupuesto!F61
A38: 11 | B38: OBRAS EXTERIORES | C38: =Presupuesto!F67
B39: TOTAL PRESUPUESTO | C39: =SUM(C28:C38)
B40: Costo por m² cubierto | C40: =C39/249.7
A42: Precios referenciales de mercado 2026 en bolivianos. Cambie los valores en la hoja «Insumos» y todo el presupuesto se recalcula. No incluye estudio de suelos, cálculo estructural, muebles, climatización, aprobación municipal, conexiones domiciliarias ni imprevistos.

Sheet Insumos
A1: Precios de insumos
A2: Edite la columna D y el presupuesto completo se actualiza
A4: Código | B4: Descripción | C4: Unidad | D4: Precio Bs
A5: MAT.cem | B5: Cemento Portland IP-30 | C5: bls 50 kg | D5: 60
A6: MAT.are | B6: Arena fina lavada | C6: m³ | D6: 160
A7: MAT.gra | B7: Gravilla 3/4" | C7: m³ | D7: 200
A8: MAT.pie | B8: Piedra bruta / bolón | C8: m³ | D8: 150
A9: MAT.lad18 | B9: Ladrillo gambote 6 huecos 18 cm | C9: pza | D9: 2
A10: MAT.lad12 | B10: Ladrillo cerámico 12 cm | C10: pza | D10: 1.8
A11: MAT.fie | B11: Fierro corrugado fy=4200 | C11: kg | D11: 11.5
A12: MAT.ala | B12: Alambre de amarre Nº 16 | C12: kg | D12: 14
A13: MAT.cla | B13: Clavos de 2" a 3" | C13: kg | D13: 16
A14: MAT.mad | B14: Madera de construcción para encofrado | C14: p² | D14: 9
A15: MAT.vig | B15: Vigueta pretensada h=15 cm | C15: ml | D15: 48
A16: MAT.pla | B16: Complemento de plastoform | C16: pza | D16: 14
... A75: EQ.and | B75: Andamio metálico modular (equipo) | C75: m² | D75: 6
B77: Los jornales son por hora, sobre jornada de 8 h. Las cargas sociales se aplican en cada análisis.

Sheet Cómputos
A1: Cómputos métricos
A2: Cantidades derivadas de la geometría del proyecto
A4: Capítulo | B4: Descripción | C4: Unidad | D4: Cantidad
A5: Movimiento de tierras
B6: Excavación de zapatas (20 u de 1,40 × 1,40 × 1,20 m) | C6: m³ | D6: 47.04
B7: Excavación de zanja de cimiento (72,00 ml × 0,50 × 1,00 m) | C7: m³ | D7: 36
B8: Relleno y compactado | C8: m³ | D8: 33.22
B9: Retiro de escombros (esponjamiento 1,25) | C9: m³ | D9: 62.28
A10: Estructura de hormigón
B11: Hormigón ciclópeo de cimiento corrido | C11: m³ | D11: 20.16
B12: H°A° en zapatas aisladas | C12: m³ | D12: 8.64
B13: H°A° en sobrecimiento y viga de arranque | C13: m³ | D13: 4.32
B14: H°A° en columnas | C14: m³ | D14: 5.61
B15: H°A° en vigas | C15: m³ | D15: 12.48
B16: Losa aligerada de entrepiso y cubierta | C16: m² | D16: 275.36
B17: Escalera de hormigón armado | C17: m² | D17: 8.1
B18: Acero de refuerzo fy = 4 200 kg/cm² | C18: kg | D18: 4143.42
B19: Encofrado de columnas y vigas | C19: m² | D19: 267.38
A20: Mampostería y revoques
B21: Muro de ladrillo gambote 18 cm (neto de vanos) | C21: m² | D21: 304.61
B22: Tabique de ladrillo 12 cm | C22: m² | D22: 84.86
B23: Parapeto de cubierta h = 0,80 m | C23: m² | D23: 36.32
B24: Revoque interior de yeso | C24: m² | D24: 590.53
B25: Revoque exterior de mortero | C25: m² | D25: 188.42
B26: Cielo raso de yeso | C26: m² | D26: 249.7
B27: Pintura interior | C27: m² | D27: 840.23
B28: Pintura exterior | C28: m² | D28: 224.74
A29: Pisos y revestimientos
B30: Contrapiso de hormigón sobre terreno | C30: m² | D30: 132
B31: Piso de porcelanato 60 × 60 cm | C31: m² | D31: 109.04
B32: Piso flotante en dormitorios | C32: m² | D32: 60.84
B33: Piso de cerámica antideslizante | C33: m² | D33: 79.82
B34: Zócalo de porcelanato | C34: ml | D34: 165
B35: Azulejo en baños h = 2,10 m | C35: m² | D35: 61.62
B36: Azulejo en cocina y lavandería | C36: m² | D36: 8
B37: Mesón de granito | C37: m² | D37: 6.06
A38: Cubierta y carpintería
B39: Impermeabilización de losa | C39: m² | D39: 128.8
B40: Bajantes pluviales Ø110 mm | C40: ml | D40: 26
B41: Puertas interiores placa | C41: pza | D41: 19
B42: Puertas exteriores | C42: pza | D42: 5
B43: Ventanas de aluminio con vidrio 6 mm | C43: m² | D43: 35.55
B44: Portón seccional de garaje | C44: pza | D44: 1
B45: Baranda metálica de balcón y escalera | C45: ml | D45: 21.8
A46: Instalaciones
B47: Puntos de agua fría | C47: pto | D47: 16
B48: Puntos de agua caliente | C48: pto | D48: 9
B49: Puntos de desagüe | C49: pto | D49: 16
B50: Colectores y bajantes Ø110 mm | C50: ml | D50: 48
B51: Cámaras de inspección | C51: pza | D51: 3
B52: Puntos de iluminación | C52: pto | D52: 42
B53: Tomacorrientes | C53: pto | D53: 48
A54: Obras exteriores
B55: Cerco perimetral h = 2,20 m | C55: m² | D55: 136.4
B56: Cerco frontal con reja | C56: ml | D56: 12
B57: Pavimento exterior de hormigón | C57: m² | D57: 56.2
B58: Pérgola de madera | C58: m² | D58: 10.5
B59: Jardinería y césped | C59: m² | D59: 120
B61: Superficies medidas sobre ejes de muro. La mampostería se computa descontando los vanos reales (445,84 m² brutos − 56,37 m² de vanos). El acero se estima en 90 kg/m³ de hormigón estructural más 4,5 kg/m² de losa; debe reemplazarse por la planilla del cálculo estructural.

Sheet APU
A1: Análisis de precios unitarios
A2: Cada precio se calcula con fórmulas enlazadas a la hoja «Insumos»
A4: ÍTEM 1.1 — Instalación de faenas (depósito, servicio sanitario, cartel de obra)
A5: Unidad | B5: glb | C5: Cantidad de obra | D5: 1
A6: Código | B6: Descripción | C6: Unidad | D6: Cantidad | E6: Precio Bs | F6: Parcial Bs
B7: 1. MATERIALES
A8: MAT.mad | B8: Madera de construcción para encofrado | C8: p² | D8: 320 | E8: =VLOOKUP($A8,Insumos!$A$5:$D$75,4,0) | F8: =ROUND(D8*E8,2)
A9: MAT.cla | B9: Clavos de 2" a 3" | C9: kg | D9: 12 | E9: =VLOOKUP($A9,Insumos!$A$5:$D$75,4,0) | F9: =ROUND(D9*E9,2)
A10: MAT.cem | B10: Cemento Portland IP-30 | C10: bls 50 kg | D10: 8 | E10: =VLOOKUP($A10,Insumos!$A$5:$D$75,4,0) | F10: =ROUND(D10*E10,2)
B11: Subtotal materiales | F11: =SUM(F8:F10)
B12: 2. MANO DE OBRA
A13: MO.mae | B13: Maestro albañil | C13: hr | D13: 24 | E13: =VLOOKUP($A13,Insumos!$A$5:$D$75,4,0) | F13: =ROUND(D13*E13,2)
A14: MO.ayu | B14: Ayudante | C14: hr | D14: 48 | E14: =VLOOKUP($A14,Insumos!$A$5:$D$75,4,0) | F14: =ROUND(D14*E14,2)
B15: Subtotal mano de obra | F15: =SUM(F13:F14)
B16: Cargas sociales 55 % | F16: =ROUND(F15*0.55,2)
B17: IVA sobre mano de obra 14.94 % | F17: =ROUND((F15+F16)*0.1494,2)
B18: Subtotal mano de obra con recargos | F18: =F15+F16+F17
B19: 3. EQUIPO Y MAQUINARIA
B20: Subtotal equipo y maquinaria | F20: 0
B21: Herramientas menores 5 % de la mano de obra | F21: =ROUND((F15+F16)*0.05,2)
B22: Subtotal equipo y herramientas | F22: =F20+F21
B23: COSTO DIRECTO (1 + 2 + 3) | F23: =F11+F18+F22
B24: Gastos generales y administrativos 10 % | F24: =ROUND(F23*0.1,2)
B25: Utilidad 7 % | F25: =ROUND((F23+F24)*0.07,2)
B26: Impuesto a las transacciones 3.09 % | F26: =ROUND((F23+F24+F25)*0.0309,2)
B27: PRECIO UNITARIO (glb) | F27: =F23+F24+F25+F26
A29: ÍTEM 1.2 — Replanteo y trazado con nivel de obra
A30: Unidad | B30: m² | C30: Cantidad de obra | D30: 132
A31: Código | B31: Descripción | C31: Unidad | D31: Cantidad | E31: Precio Bs | F31: Parcial Bs
B32: 1. MATERIALES
A33: MAT.mad | B33: Madera de construcción para encofrado | C33: p² | D33: 0.35 | E33: =VLOOKUP($A33,Insumos!$A$5:$D$75,4,0) | F33: =ROUND(D33*E33,2)
A34: MAT.cla | B34: Clavos de 2" a 3" | C34: kg | D34: 0.05 | E34: =VLOOKUP($A34,Insumos!$A$5:$D$75,4,0) | F34: =ROUND(D34*E34,2)
B35: Subtotal materiales | F35: =SUM(F33:F34)
B36: 2. MANO DE OBRA
A37: MO.mae | B37: Maestro albañil | C37: hr | D37: 0.09 | E37: =VLOOKUP($A37,Insumos!$A$5:$D$75,4,0) | F37: =ROUND(D37*E37,2)
A38: MO.ayu | B38: Ayudante | C38: hr | D38: 0.18 | E38: =VLOOKUP($A38,Insumos!$A$5:$D$75,4,0) | F38: =ROUND(D38*E38,2)
B39: Subtotal mano de obra | F39: =SUM(F37:F38)
B40: Cargas sociales 55 % | F40: =ROUND(F39*0.55,2)
B41: IVA sobre mano de obra 14.94 % | F41: =ROUND((F39+F40)*0.1494,2)
B42: Subtotal mano de obra con recargos | F42: =F39+F40+F41
B43: 3. EQUIPO Y MAQUINARIA
B44: Subtotal equipo y maquinaria | F44: 0
B45: Herramientas menores 5 % de la mano de obra | F45: =ROUND((F39+F40)*0.05,2)
B46: Subtotal equipo y herramientas | F46: =F44+F45
B47: COSTO DIRECTO (1 + 2 + 3) | F47: =F35+F42+F46
B48: Gastos generales y administrativos 10 % | F48: =ROUND(F47*0.1,2)
B49: Utilidad 7 % | F49: =ROUND((F47+F48)*0.07,2)
B50: Impuesto a las transacciones 3.09 % | F50: =ROUND((F47+F48+F49)*0.0309,2)
B51: PRECIO UNITARIO (m²) | F51: =F47+F48+F49+F50
A53: ÍTEM 2.1 — Excavación manual de zapatas, suelo semiduro h≤1,20 m
A54: Unidad | B54: m³ | C54: Cantidad de obra | D54: 47.04
A55: Código | B55: Descripción | C55: Unidad | D55: Cantidad | E55: Precio Bs | F55: Parcial Bs
B56: 1. MATERIALES
B57: Subtotal materiales | F57: 0
B58: 2. MANO DE OBRA
A59: MO.alb | B59: Albañil | C59: hr | D59: 0.35 | E59: =VLOOKUP($A59,Insumos!$A$5:$D$75,4,0) | F59: =ROUND(D59*E59,2)
A60: MO.ayu | B60: Ayudante | C60: hr | D60: 2.1 | E60: =VLOOKUP($A60,Insumos!$A$5:$D$75,4,0) | F60: =ROUND(D60*E60,2)
B61: Subtotal mano de obra | F61: =SUM(F59:F60)
B62: Cargas sociales 55 % | F62: =ROUND(F61*0.55,2)
B63: IVA sobre mano de obra 14.94 % | F63: =ROUND((F61+F62)*0.1494,2)
B64: Subtotal mano de obra con recargos | F64: =F61+F62+F63
B65: 3. EQUIPO Y MAQUINARIA
B66: Subtotal equipo y maquinaria | F66: 0
B67: Herramientas menores 5 % de la mano de obra | F67: =ROUND((F61+F62)*0.05,2)
B68: Subtotal equipo y herramientas | F68: =F66+F67
B69: COSTO DIRECTO (1 + 2 + 3) | F69: =F57+F64+F68
B70: Gastos generales y administrativos 10 % | F70: =ROUND(F69*0.1,2)
B71: Utilidad 7 % | F71: =ROUND((F69+F70)*0.07,2)
B72: Impuesto a las transacciones 3.09 % | F72: =ROUND((F69+F70+F71)*0.0309,2)
B73: PRECIO UNITARIO (m³) | F73: =F69+F70+F71+F72
A75: ÍTEM 2.2 — Excavación manual de zanja para cimiento corrido
A76: Unidad | B76: m³ | C76: Cantidad de obra | D76: 36
A77: Código | B77: Descripción | C77: Unidad | D77: Cantidad | E77: Precio Bs | F77: Parcial Bs
B78: 1. MATERIALES
B79: Subtotal materiales | F79: 0
B80: 2. MANO DE OBRA
A81: MO.alb | B81: Albañil | C81: hr | D81: 0.3 | E81: =VLOOKUP($A81,Insumos!$A$5:$D$75,4,0) | F81: =ROUND(D81*E81,2)
A82: MO.ayu | B82: Ayudante | C82: hr | D82: 1.9 | E82: =VLOOKUP($A82,Insumos!$A$5:$D$75,4,0) | F82: =ROUND(D82*E82,2)
B83: Subtotal mano de obra | F83: =SUM(F81:F82)
B84: Cargas sociales 55 % | F84: =ROUND(F83*0.55,2)
B85: IVA sobre mano de obra 14.94 % | F85: =ROUND((F83+F84)*0.1494,2)
B86: Subtotal mano de obra con recargos | F86: =F83+F84+F85
B87: 3. EQUIPO Y MAQUINARIA
B88: Subtotal equipo y maquinaria | F88: 0
B89: Herramientas menores 5 % de la mano de obra | F89: =ROUND((F83+F84)*0.05,2)
B90: Subtotal equipo y herramientas | F90: =F88+F89
B91: COSTO DIRECTO (1 + 2 + 3) | F91: =F79+F86+F90
B92: Gastos generales y administrativos 10 % | F92: =ROUND(F91*0.1,2)
B93: Utilidad 7 % | F93: =ROUND((F91+F92)*0.07,2)
B94: Impuesto a las transacciones 3.09 % | F94: =ROUND((F91+F92+F93)*0.0309,2)
B95: PRECIO UNITARIO (m³) | F95: =F91+F92+F93+F94
A97: ÍTEM 2.3 — Relleno y compactado con material seleccionado, capas de 0,20 m
A98: Unidad | B98: m³ | C98: Cantidad de obra | D98: 33.22
A99: Código | B99: Descripción | C99: Unidad | D99: Cantidad | E99: Precio Bs | F99: Parcial Bs
B100: 1. MATERIALES
B101: Subtotal materiales | F101: 0
B102: 2. MANO DE OBRA
A103: MO.alb | B103: Albañil | C103: hr | D103: 0.25 | E103: =VLOOKUP($A103,Insumos!$A$5:$D$75,4,0) | F103: =ROUND(D103*E103,2)
A104: MO.ayu | B104: Ayudante | C104: hr | D104: 1.2 | E104: =VLOOKUP($A104,Insumos!$A$5:$D$75,4,0) | F104: =ROUND(D104*E104,2)
B105: Subtotal mano de obra | F105: =SUM(F103:F104)
...

Sheet Presupuesto
A1: Presupuesto general
A2: Los precios unitarios vienen de la hoja «APU»; las cantidades, de «Cómputos»
A4: Ítem | B4: Descripción | C4: Unidad | D4: Cantidad | E4: P. unitario Bs | F4: Parcial Bs
A5: 1 | B5: TRABAJOS PRELIMINARES | F5: =SUM(F6:F7)
A6: 1.1 | B6: Instalación de faenas (depósito, servicio sanitario, cartel de obra) | C6: glb | D6: 1 | E6: =APU!F27 | F6: =ROUND(D6*E6,2)
A7: 1.2 | B7: Replanteo y trazado con nivel de obra | C7: m² | D7: 132 | E7: =APU!F51 | F7: =ROUND(D7*E7,2)
A8: 2 | B8: MOVIMIENTO DE TIERRAS | F8: =SUM(F9:F12)
A9: 2.1 | B9: Excavación manual de zapatas, suelo semiduro h≤1,20 m | C9: m³ | D9: 47.04 | E9: =APU!F73 | F9: =ROUND(D9*E9,2)
A10: 2.2 | B10: Excavación manual de zanja para cimiento corrido | C10: m³ | D10: 36 | E10: =APU!F95 | F10: =ROUND(D10*E10,2)
A11: 2.3 | B11: Relleno y compactado con material seleccionado, capas de 0,20 m | C11: m³ | D11: 33.22 | E11: =APU!F118 | F11: =ROUND(D11*E11,2)
A12: 2.4 | B12: Retiro de escombros y tierra sobrante hasta 10 km | C12: m³ | D12: 62.28 | E12: =APU!F141 | F12: =ROUND(D12*E12,2)
A13: 3 | B13: OBRA GRUESA: HORMIGONES Y ESTRUCTURA | F13: =SUM(F14:F20)
A14: 3.1 | B14: Hormigón ciclópeo 50 % piedra desplazadora para cimiento corrido | C14: m³ | D14: 20.16 | E14: =APU!F169 | F14: =ROUND(D14*E14,2)
A15: 3.2 | B15: Hormigón armado fc=210 kg/cm² en zapatas aisladas | C15: m³ | D15: 8.64 | E15: =APU!F200 | F15: =ROUND(D15*E15,2)
A16: 3.3 | B16: Hormigón armado fc=210 en sobrecimiento y viga de arranque 0,20 × 0,30 | C16: m³ | D16: 4.32 | E16: =APU!F232 | F16: =ROUND(D16*E16,2)
A17: 3.4 | B17: Hormigón armado fc=210 en columnas 0,20 × 0,25 | C17: m³ | D17: 5.61 | E17: =APU!F265 | F17: =ROUND(D17*E17,2)
A18: 3.5 | B18: Hormigón armado fc=210 en vigas 0,20 × 0,30 | C18: m³ | D18: 12.48 | E18: =APU!F298 | F18: =ROUND(D18*E18,2)
A19: 3.6 | B19: Losa aligerada e=0,20 m con viguetas pretensadas y plastoform | C19: m² | D19: 275.36 | E19: =APU!F333 | F19: =ROUND(D19*E19,2)
A20: 3.7 | B20: Escalera de hormigón armado con peldaños conformados | C20: m² | D20: 8.1 | E20: =APU!F364 | F20: =ROUND(D20*E20,2)
A21: 4 | B21: MAMPOSTERÍA Y CERRAMIENTOS | F21: =SUM(F22:F24)
A22: 4.1 | B22: Muro de ladrillo gambote de 18 cm con mortero 1:5 | C22: m² | D22: 304.61 | E22: =APU!F392 | F22: =ROUND(D22*E22,2)
A23: 4.2 | B23: Tabique de ladrillo cerámico de 12 cm con mortero 1:5 | C23: m² | D23: 84.86 | E23: =APU!F420 | F23: =ROUND(D23*E23,2)
A24: 4.3 | B24: Parapeto de cubierta h=0,80 m, ladrillo 12 cm con viga de coronamiento | C24: m² | D24: 36.32 | E24: =APU!F448 | F24: =ROUND(D24*E24,2)
A25: 5 | B25: REVOQUES, CIELOS Y PINTURA | F25: =SUM(F26:F30)
A26: 5.1 | B26: Revoque interior de yeso sobre muro, e=1,5 cm | C26: m² | D26: 590.53 | E26: =APU!F474 | F26: =ROUND(D26*E26,2)
A27: 5.2 | B27: Revoque exterior de mortero 1:4 con acabado frotachado, e=2 cm | C27: m² | D27: 188.42 | E27: =APU!F501 | F27: =ROUND(D27*E27,2)
A28: 5.3 | B28: Cielo raso de yeso bajo losa con malla y perfilería | C28: m² | D28: 249.7 | E28: =APU!F526 | F28: =ROUND(D28*E28,2)
A29: 5.4 | B29: Pintura látex interior, sellador y dos manos | C29: m² | D29: 840.23 | E29: =APU!F552 | F29: =ROUND(D29*E29,2)
A30: 5.5 | B30: Pintura látex acrílica exterior, imprimante y dos manos | C30: m² | D30: 224.74 | E30: =APU!F577 | F30: =ROUND(D30*E30,2)
A31: 6 | B31: PISOS Y REVESTIMIENTOS | F31: =SUM(F32:F39)
A32: 6.1 | B32: Contrapiso de hormigón simple e=7 cm sobre terreno compactado | C32: m² | D32: 132 | E32: =APU!F605 | F32: =ROUND(D32*E32,2)
A33: 6.2 | B33: Piso de porcelanato 60 × 60 cm con pegamento y fragua | C33: m² | D33: 109.04 | E33: =APU!F630 | F33: =ROUND(D33*E33,2)
A34: 6.3 | B34: Piso flotante AC4 de 8 mm con manta y zócalo perimetral | C34: m² | D34: 60.84 | E34: =APU!F654 | F34: =ROUND(D34*E34,2)
A35: 6.4 | B35: Piso de cerámica antideslizante 45 × 45 cm | C35: m² | D35: 79.82 | E35: =APU!F679 | F35: =ROUND(D35*E35,2)
A36: 6.5 | B36: Zócalo de porcelanato h=7 cm | C36: ml | D36: 165 | E36: =APU!F704 | F36: =ROUND(D36*E36,2)
A37: 6.6 | B37: Revestimiento de azulejo en baños h=2,10 m | C37: m² | D37: 61.62 | E37: =APU!F729 | F37: =ROUND(D37*E37,2)
A38: 6.7 | B38: Revestimiento de azulejo en mesón de cocina y lavandería | C38: m² | D38: 8 | E38: =APU!F754 | F38: =ROUND(D38*E38,2)
A39: 6.8 | B39: Mesón de granito natural e=2 cm con pulido de bordes | C39: m² | D39: 6.06 | E39: =APU!F778 | F39: =ROUND(D39*E39,2)
A40: 7 | B40: CUBIERTA | F40: =SUM(F41:F42)
A41: 7.1 | B41: Impermeabilización de losa con membrana asfáltica 4 mm y carpeta de pendiente | C41: m² | D41: 128.8 | E41: =APU!F805 | F41: =ROUND(D41*E41,2)
A42: 7.2 | B42: Bajante pluvial de PVC Ø110 mm con abrazaderas y rejilla | C42: ml | D42: 26 | E42: =APU!F829 | F42: =ROUND(D42*E42,2)
A43: 8 | B43: CARPINTERÍA | F43: =SUM(F44:F48)
A44: 8.1 | B44: Puerta placa 0,90 × 2,10 m con marco de madera y quincallería | C44: pza | D44: 19 | E44: =APU!F854 | F44: =ROUND(D44*E44,2)
A45: 8.2 | B45: Puerta exterior de madera tablero con marco reforzado y cerradura de seguridad | C45: pza | D45: 5 | E45: =APU!F879 | F45: =ROUND(D45*E45,2)
A46: 8.3 | B46: Ventana de aluminio línea 25 con vidrio de 6 mm, incluye contramarco | C46: m² | D46: 35.55 | E46: =APU!F904 | F46: =ROUND(D46*E46,2)
A47: 8.4 | B47: Portón seccional de garaje 4,40 × 2,30 m con guías y resortes | C47: pza | D47: 1 | E47: =APU!F928 | F47: =ROUND(D47*E47,2)
A48: 8.5 | B48: Baranda metálica de balcón y escalera con pasamanos | C48: ml | D48: 21.8 | E48: =APU!F952 | F48: =ROUND(D48*E48,2)
A49: 9 | B49: INSTALACIÓN SANITARIA Y AGUA | F49: =SUM(F50:F60)
A50: 9.1 | B50: Punto de agua fría PPR Ø1/2" con llave de paso | C50: pto | D50: 16 | E50: =APU!F977 | F50: =ROUND(D50*E50,2)
A51: 9.2 | B51: Punto de agua caliente PPR Ø1/2" con aislamiento | C51: pto | D51: 9 | E51: =APU!F1002 | F51: =ROUND(D51*E51,2)
A52: 9.3 | B52: Punto de desagüe PVC Ø50 a Ø110 mm con sifón y ventilación | C52: pto | D52: 16 | E52: =APU!F1028 | F52: =ROUND(D52*E52,2)
A53: 9.4 | B53: Colector y bajante de PVC Ø110 mm con pendiente 2 % | C53: ml | D53: 48 | E53: =APU!F1052 | F53: =ROUND(D53*E53,2)
A54: 9.5 | B54: Cámara de inspección 0,60 × 0,60 m con tapa de H°A° | C54: pza | D54: 3 | E54: =APU!F1080 | F54: =ROUND(D54*E54,2)
A55: 9.6 | B55: Provisión e instalación de inodoro con tanque bajo | C55: pza | D55: 4 | E55: =APU!F1104 | F55: =ROUND(D55*E55,2)
A56: 9.7 | B56: Provisión e instalación de lavamanos con grifería | C56: pza | D56: 4 | E56: =APU!F1128 | F56: =ROUND(D56*E56,2)
A57: 9.8 | B57: Provisión e instalación de grifería de ducha monocomando | C57: pza | D57: 4 | E57: =APU!F1152 | F57: =ROUND(D57*E57,2)
A58: 9.9 | B58: Fregadero de cocina de 2 pozas y batea de lavandería | C58: pza | D58: 2 | E58: =APU!F1177 | F58: =ROUND(D58*E58,2)
A59: 9.10 | B59: Tanque de reserva 1 000 L con bomba, presostato y accesorios | C59: glb | D59: 1 | E59: =APU!F1203 | F59: =ROUND(D59*E59,2)
A60: 9.11 | B60: Termotanque eléctrico de 80 L instalado | C60: pza | D60: 1 | E60: =APU!F1228 | F60: =ROUND(D60*E60,2)
A61: 10 | B61: INSTALACIÓN ELÉCTRICA | F61: =SUM(F62:F66)
A62: 10.1 | B62: Punto de iluminación con ducto, cable 2,5 mm², caja e interruptor | C62: pto | D62: 42 | E62: =APU!F1255 | F62: =ROUND(D62*E62,2)
A63: 10.2 | B63: Punto de tomacorriente doble con puesta a tierra | C63: pto | D63: 48 | E63: =APU!F1281 | F63: =ROUND(D63*E63,2)
A64: 10.3 | B64: Tablero de distribución 12 polos con diferencial y térmicas | C64: pza | D64: 1 | E64: =APU!F1306 | F64: =ROUND(D64*E64,2)
A65: 10.4 | B65: Acometida, medidor y puesta a tierra con jabalina | C65: glb | D65: 1 | E65: =APU!F1331 | F65: =ROUND(D65*E65,2)
A66: 10.5 | B66: Previsión para sistema fotovoltaico: ducto, cableado y tablero en cubierta | C66: glb | D66: 1 | E66: =APU!F1356 | F66: =ROUND(D66*E66,2)
A67: 11 | B67: OBRAS EXTERIORES | F67: =SUM(F68:F74)
A68: 11.1 | B68: Cerco perimetral de ladrillo visto h=2,20 m con columnetas y viga | C68: m² | D68: 136.4 | E68: =APU!F1383 | F68: =ROUND(D68*E68,2)
A69: 11.2 | B69: Cerco frontal: zócalo de 1,00 m y reja metálica de 1,20 m | C69: ml | D69: 12 | E69: =APU!F1410 | F69: =ROUND(D69*E69,2)
A70: 11.3 | B70: Portón vehicular metálico 4,80 × 1,60 m y portón peatonal 1,50 m | C70: glb | D70: 1 | E70: =APU!F1436 | F70: =ROUND(D70*E70,2)
A71: 11.4 | B71: Pavimento exterior de hormigón e=10 cm con malla y juntas | C71: m² | D71: 56.2 | E71: =APU!F1464 | F71: =ROUND(D71*E71,2)
A72: 11.5 | B72: Churrasquera con mesón, parrilla y chimenea de ladrillo visto | C72: glb | D72: 1 | E72: =APU!F1493 | F72: =ROUND(D72*E72,2)
A73: 11.6 | B73: Pérgola de madera dura con vigas 0,10 × 0,20 m y listones | C73: m² | D73: 10.5 | E73: =APU!F1519 | F73: =ROUND(D73*E73,2)
A74: 11.7 | B74: Jardinería: tierra vegetal, césped y limpieza final de obra | C74: m² | D74: 120 | E74: =APU!F1543 | F74: =ROUND(D74*E74,2)
B76: TOTAL PRESUPUESTO (Bs) | F76: =F5+F8+F13+F21+F25+F31+F40+F43+F49+F61+F67
B77: Costo por m² cubierto (249,70 m²) | F77: =F76/249.7
